sctk/.ipynb_checkpoints/Untitled-checkpoint.ipynb
sctk/.ipynb_checkpoints/_pipeline-checkpoint.py
sctk/.ipynb_checkpoints/_plot-checkpoint.py
sctk/Untitled.ipynb
sctk/__init__.py
sctk/_annot.py
sctk/_diffexp.py
sctk/_diffmap.py
sctk/_doublets.py
sctk/_dpt.py
sctk/_fdg.py
sctk/_filter.py
sctk/_highly_deviant_genes.py
sctk/_hvg.py
sctk/_leiden.py
sctk/_louvain.py
sctk/_markers.py
sctk/_neighbors.py
sctk/_norm.py
sctk/_obj_utils.py
sctk/_paga.py
sctk/_pca.py
sctk/_pipeline.py
sctk/_plot.py
sctk/_read.py
sctk/_tsne.py
sctk/_umap.py
sctk/_utils.py
sctk/_velocity.py
sctk-0.2.4.dist-info/METADATA
sctk-0.2.4.dist-info/WHEEL
sctk-0.2.4.dist-info/licenses/LICENSE
sctk-0.2.4.dist-info/RECORD
