Metadata-Version: 2.4
Name: sctk
Version: 0.2.4
Summary: single cell analysis tool kit based on scanpy
License: GPL-3.0
License-File: LICENSE
Author: nh3
Author-email: nh3@users.noreply.github.com
Requires-Python: >=3.9,<4.0
Classifier: License :: OSI Approved :: GNU General Public License v3 (GPLv3)
Classifier: Programming Language :: Python :: 3
Classifier: Programming Language :: Python :: 3.9
Classifier: Programming Language :: Python :: 3.10
Classifier: Programming Language :: Python :: 3.11
Classifier: Programming Language :: Python :: 3.12
Classifier: Programming Language :: Python :: 3.13
Classifier: Programming Language :: Python :: 3.14
Requires-Dist: adjustText (>=0.8,<0.9)
Requires-Dist: harmonypy (>=0.0.9,<0.0.10)
Requires-Dist: leidenalg (>=0.10.0,<0.11.0)
Requires-Dist: numpy-groupies (>=0.9.22,<0.10.0)
Requires-Dist: scanpy (>=1.9.3,<2.0.0)
Project-URL: Documentation, https://teichlab.github.io/sctk/
Project-URL: Homepage, https://github.com/Teichlab/sctk
